rd2md.py
rd_to_md-0.0.3.dist-info/METADATA
rd_to_md-0.0.3.dist-info/WHEEL
rd_to_md-0.0.3.dist-info/entry_points.txt
rd_to_md-0.0.3.dist-info/top_level.txt
rd_to_md-0.0.3.dist-info/RECORD
