Metadata-Version: 2.1
Name: rd-to-md
Version: 0.0.3
Summary: Scrape reddit posts into a single markdown file
Home-page: https://github.com/JosefAlbers/rd2md
Author: Josef Albers
Author-email: albersj66@gmail.com
License: MIT
Requires-Python: >=3.12.3
Requires-Dist: praw ==7.7.1
Requires-Dist: markdown ==3.6
Requires-Dist: requests ==2.32.3
